clean_architecture_linter/__init__.py
clean_architecture_linter/checker.py
clean_architecture_linter/cli.py
clean_architecture_linter/config.py
clean_architecture_linter/constants.py
clean_architecture_linter/helpers.py
clean_architecture_linter/layer_registry.py
clean_architecture_linter/reporter.py
clean_architecture_linter/checks/__init__.py
clean_architecture_linter/checks/boundaries.py
clean_architecture_linter/checks/bypass.py
clean_architecture_linter/checks/contracts.py
clean_architecture_linter/checks/dependencies.py
clean_architecture_linter/checks/design.py
clean_architecture_linter/checks/di.py
clean_architecture_linter/checks/immutability.py
clean_architecture_linter/checks/patterns.py
clean_architecture_linter/checks/structure.py
clean_architecture_linter/checks/testing.py
pylint_clean_architecture-1.5.2.dist-info/licenses/LICENSE
pylint_clean_architecture-1.5.2.dist-info/METADATA
pylint_clean_architecture-1.5.2.dist-info/WHEEL
pylint_clean_architecture-1.5.2.dist-info/entry_points.txt
pylint_clean_architecture-1.5.2.dist-info/top_level.txt
pylint_clean_architecture-1.5.2.dist-info/RECORD
