Metadata-Version: 2.4
Name: pylint-clean-architecture
Version: 1.5.2
Summary: Excelsior: High-fidelity clean architecture linter for Python.
Author: Antigravity Team
License: MIT
Classifier: Development Status :: 3 - Alpha
Classifier: Intended Audience :: Developers
Classifier: License :: OSI Approved :: MIT License
Classifier: Programming Language :: Python :: 3.10
Classifier: Programming Language :: Python :: 3.11
Classifier: Programming Language :: Python :: 3.12
Classifier: Programming Language :: Python :: 3.13
Classifier: Programming Language :: Python :: 3.14
Requires-Python: >=3.9
License-File: LICENSE
Requires-Dist: pylint>=2.15.0
Requires-Dist: tomli; python_version < "3.11"
Provides-Extra: dev
Requires-Dist: pytest>=7.0; extra == "dev"
Requires-Dist: pytest-cov>=4.0; extra == "dev"
Requires-Dist: astroid; extra == "dev"
Requires-Dist: ruff; extra == "dev"
Dynamic: license-file
